oauth_ssh/__init__.py
oauth_ssh/account_map.py
oauth_ssh/config.py
oauth_ssh/constants.py
oauth_ssh/credential.py
oauth_ssh/exceptions.py
oauth_ssh/globus_auth.py
oauth_ssh/oauth_ssh.py
oauth_ssh/oauth_ssh_token.py
oauth_ssh/policy.py
oauth_ssh/ssh_service.py
oauth_ssh/template.py
oauth_ssh/token.py
oauth_ssh/transport.py
oauth_ssh-0.14.dist-info/DESCRIPTION.rst
oauth_ssh-0.14.dist-info/METADATA
oauth_ssh-0.14.dist-info/RECORD
oauth_ssh-0.14.dist-info/WHEEL
oauth_ssh-0.14.dist-info/entry_points.txt
oauth_ssh-0.14.dist-info/metadata.json
oauth_ssh-0.14.dist-info/top_level.txt
